sample/__init__.py
sample/core.py
sample/helpers.py
yanwang_sample-0.1.0.dist-info/DESCRIPTION.rst
yanwang_sample-0.1.0.dist-info/METADATA
yanwang_sample-0.1.0.dist-info/RECORD
yanwang_sample-0.1.0.dist-info/WHEEL
yanwang_sample-0.1.0.dist-info/metadata.json
yanwang_sample-0.1.0.dist-info/top_level.txt
