Metadata-Version: 2.0
Name: yanwang-sample
Version: 0.1.0
Summary: Sample package for Python-Guide.org
Home-page: https://github.com/kennethreitz/samplemod
Author: Kenneth Reitz
Author-email: me@kennethreitz.com
License: Copyright (c) 2017, Kenneth Reitz
